[{"Id":"7ddc2ebc-767f-4c57-bfea-a61ee710f5c8","FullName":"test 3","FlightNumber":"aa112","DepartureDate":"2024-12-27T13:35:00Z","ArrivalDate":"2024-12-28T13:50:00Z","TicketType":0},{"Id":"61ebaa99-462b-4a5b-8075-512fd051fae5","FullName":"test 3","FlightNumber":"aa112","DepartureDate":"2024-12-27T16:35:00.702Z","ArrivalDate":"2024-12-28T16:35:00.702Z","TicketType":1},{"Id":"ad45f81d-86b1-4f2f-9a59-89b043364ebc","FullName":"test 3","FlightNumber":"aa112","DepartureDate":"2024-12-27T15:35:00Z","ArrivalDate":"2024-12-28T15:35:00Z","TicketType":1},{"Id":"e7094493-5d5f-4065-b237-fe91c5ddd0fe","FullName":"test 3","FlightNumber":"aa112","DepartureDate":"2024-12-27T16:35:00.702Z","ArrivalDate":"2024-12-28T16:35:00.702Z","TicketType":1},{"Id":"d36e9a83-06b9-426b-ab62-76a6640571e4","FullName":"test 3","FlightNumber":"aa112","DepartureDate":"2024-12-27T16:35:00.702Z","ArrivalDate":"2024-12-28T16:35:00.702Z","TicketType":1},{"Id":"c2bd065e-eedd-410d-ab96-b78934e3c714","FullName":"test 3","FlightNumber":"aa112","DepartureDate":"2024-12-27T16:35:00.702Z","ArrivalDate":"2024-12-28T16:35:00.702Z","TicketType":1},{"Id":"df448966-dc35-478b-950b-6b81b884234a","FullName":"test 3","FlightNumber":"aa112","DepartureDate":"2024-12-27T16:35:00.702Z","ArrivalDate":"2024-12-28T16:35:00.702Z","TicketType":1},{"Id":"326596c8-0ace-4b96-95f7-ec31e64f4593","FullName":"test 3","FlightNumber":"aa112","DepartureDate":"2024-12-27T16:35:00.702Z","ArrivalDate":"2024-12-28T16:35:00.702Z","TicketType":1},{"Id":"39e8f187-eb3c-48a1-82a8-9679448f1ca2","FullName":"test 3","FlightNumber":"aa112","DepartureDate":"2024-12-27T16:35:00.702Z","ArrivalDate":"2024-12-28T16:35:00.702Z","TicketType":1},{"Id":"a566bc2f-9c02-4e4f-b568-5b0e5e18635c","FullName":"test 3","FlightNumber":"aa112","DepartureDate":"2024-12-27T16:35:00.702Z","ArrivalDate":"2024-12-28T16:35:00.702Z","TicketType":1},{"Id":"d9aa7222-765d-4ac0-98f8-376019c16424","FullName":"test 3","FlightNumber":"aa112","DepartureDate":"2024-12-27T16:35:00.702Z","ArrivalDate":"2024-12-28T16:35:00.702Z","TicketType":1},{"Id":"9457fbad-7ba5-4a02-967c-2b2f4c00b522","FullName":"test 3","FlightNumber":"aa112","DepartureDate":"2024-12-27T16:35:00.702Z","ArrivalDate":"2024-12-28T16:35:00.702Z","TicketType":1},{"Id":"5c9626a7-0e3e-41e9-a1b7-7e0718fa3f04","FullName":"test 3","FlightNumber":"aa112","DepartureDate":"2024-12-27T16:35:00.702Z","ArrivalDate":"2024-12-28T16:35:00.702Z","TicketType":1},{"Id":"ff44f5e7-adee-4c33-a26a-4d79a8c831f3","FullName":"test 3","FlightNumber":"aa112","DepartureDate":"2024-12-27T16:35:00.702Z","ArrivalDate":"2024-12-28T16:35:00.702Z","TicketType":1},{"Id":"d7ae7ace-c927-4a3c-8170-75e9e17f65ec","FullName":"test 3","FlightNumber":"aa112","DepartureDate":"2024-12-27T16:35:00.702Z","ArrivalDate":"2024-12-28T16:35:00.702Z","TicketType":1},{"Id":"b8d26f04-8ab6-4230-ac1d-a5337e1f51cd","FullName":"TESTOWANIE","FlightNumber":"AA555","DepartureDate":"2001-01-01T12:23:00","ArrivalDate":"2002-02-02T12:23:00","TicketType":0}]